# 构建JVM语言 - Enkel

<h2 align="center">【第十一节】：默认参数</h2>

</br>

[原文](http://jakubdziworski.github.io/enkel/2016/04/17/enkel_11_default_parameters.html)

</br>

## Java和默认参数

在Java中，缺少默认参数是我讨厌的其中一件事。有人建议使用建造者模式，但是这种解决方案会导致大量的样板（boilerplate）代码。我不知道为什么Java团队这么长时间一直忽略这个功能。事实证明，实现起来并不难。

## Argument vs Parameter

这两个术语经常会被混淆，但是其实它们拥有不同的含义。最简单的表达方式就是：

- parameter - 方法签名
- argument - 方法调用

argument是指在调用函数时传递的表达式。parameter是指方法签名中的一个变量。

## 概念

这个主意是在调用过程中查找方法签名，并从中获取参数的默认值。这样就无需修改字节码。函数调用仅“模拟”一个默认值，就好像它是显式传递一样。

## 语法变更

`functionParameterRule`仅有一个小变化：

```antlr
functionParameter : type ID functionParamdefaultValue? ;
functionParamdefaultValue : '=' expression ;
```

方法参数包含类型，后面跟名称。可选符号（（‘?’）后面跟等于号（‘=’），然后跟一些默认表达式。

## 适配antlr上下文对象

这一节改动很小。在`FunctionParameter`类中引入了新的字段`defaultValue`。

这个字段存储了`Optional<Expression>`对象。如果解析器发现了默认值，则Optional包含这个值，否则Optional是空的。

```java
public class FunctionSignatureVisitor extends EnkelBaseVisitor<FunctionSignature> {

    @Override
    public FunctionSignature visitFunctionDeclaration(@NotNull EnkelParser.FunctionDeclarationContext ctx) {
       //other stuff
        for(int i=0;i<argsCtx.size();i++) { //for each parsed argument
        //other stuff
            Optional<Expression> defaultValue = getParameterDefaultValue(argCtx);
            FunctionParameter functionParameters = new FunctionParameter(name, type, defaultValue);
            parameters.add(functionParameters);
        }
        //other stuff
    }

    private Optional<Expression> getParameterDefaultValue(FunctionParameterContext argCtx) {
        if(argCtx.functionParamdefaultValue() != null) {
            EnkelParser.ExpressionContext defaultValueCtx = argCtx.functionParamdefaultValue().expression();
            return Optional.of(defaultValueCtx.accept(expressionVisitor));
        }
        return Optional.empty();
    }
}
```

## 生成字节码

生成用于函数调用的字节码必须执行以下步骤：

- 检查方法调用的参数是否比方法签名的参数多
- 获取并评估缺少参数的默认表达式

“缺少“的参数定义为签名中的最后一个索引（不包含）和函数调用中的最后一个索引（包含）之间的索引参数。

示例：

签名：fun(int x, int x2 = 5, int x3 = 4)

调用：fun(2)

缺少的参数是x2（索引1）和x3（索引2），因为函数调用中最后一个索引是0，函数签名中最后一个索引是2。

```java
public class ExpressionGenrator {
    public void generate(FunctionCall functionCall) {
        //other stuff
        if(arguments.size() > parameters.size()) {  
            throw new BadArgumentsToFunctionCallException(functionCall);
        }
        arguments.forEach(argument -> argument.accept(this));
        for(int i=arguments.size();i<parameters.size();i++) {
            Expression defaultParameter = parameters.get(i).getDefaultValue()
                    .orElseThrow(() -> new BadArgumentsToFunctionCallException(functionCall));
            defaultParameter.accept(this);
        }
        //other stuff   
    }
}
```

## 示例

下面的Enkel类：

```groovy
DefaultParamTest {

    main(string[] args) {
         greet("andrew")
         print ""
         greet("kuba","enkel")
    }

    greet (string name,string favouriteLanguage="java") {
        print "Hello my name is "
        print name
        print "and my favourite langugage is "
        print favouriteLanguage
    }
}
```

编译后的字节码如下所示：

```shell
kuba@kuba-laptop:~/repos/Enkel-JVM-language$ javap -c DefaultParamTest
public class DefaultParamTest {
  public static void main(java.lang.String[]);
    Code:
       0: ldc           #8                  //push String "andrew" onto the stack
       2: ldc           #10   // push String "java" onto the stack  <-- implicit argument value
       4: invokestatic  #14                 // invoke static method greet:(Ljava/lang/String;Ljava/lang/String;)V
       7: getstatic     #20                 // get static field java/lang/System.out:Ljava/io/PrintStream;
      10: ldc           #22                 // push  empty String (empty line)
      12: invokevirtual #27                 // call Method "Ljava/io/PrintStream;".println:(Ljava/lang/String;)V to print empty line
      15: ldc           #29                 // push String "kuba"
      17: ldc           #31   // push String "enkel" <-- explicit argument value
      19: invokestatic  #14                 //invoke static method greet:(Ljava/lang/String;Ljava/lang/String;)V
      22: return

  public static void greet(java.lang.String, java.lang.String);
    Code:
       0: getstatic     #20                 // Field java/lang/System.out:Ljava/io/PrintStream;
       3: ldc           #33                 // String Hello my name is
       5: invokevirtual #27                 // Method "Ljava/io/PrintStream;".println:(Ljava/lang/String;)V
       8: getstatic     #20                 // Field java/lang/System.out:Ljava/io/PrintStream;
      11: aload_0                           // load (push onto stack) variable at index 0 (first parameter of a method)
      12: invokevirtual #27                 // Method "Ljava/io/PrintStream;".println:(Ljava/lang/String;)V
      15: getstatic     #20                 // Field java/lang/System.out:Ljava/io/PrintStream;
      18: ldc           #35                 // String and my favourite langugage is
      20: invokevirtual #27                 // Method "Ljava/io/PrintStream;".println:(Ljava/lang/String;)V
      23: getstatic     #20                 // Field java/lang/System.out:Ljava/io/PrintStream;
      26: aload_1                           // load (push onto stack) variable at index 1 (second parameter of a method)
      27: invokevirtual #27                 // Method "Ljava/io/PrintStream;".println:(Ljava/lang/String;)V
      30: return
}
```

并且输出是：

```shell
Hello my name is 
andrew
and my favourite langugage is 
java

Hello my name is 
kuba
and my favourite langugage is 
enkel
```

</br></br></br>

<div align="left"><a href="./09-条件语句.md">上一节</a></div>

<div align="left"><a href="./11-函数参数命名.md">下一节</a></div>