# 构建JVM语言 - Enkel

<h2 align="center">【第十六节】：埋葬静态属性</h2>

</br>

[原文](http://jakubdziworski.github.io/enkel/2016/05/09/enkel_16_ditching_static.html)

</br>

## 源码

这个项目的源码可以从[Github仓库](https://github.com/JakubDziworski/Enkel-JVM-language)中进行克隆。

## OOP和静态属性

面向对象编程的最大优势是什么？我认为是多态性（polymorphism）。你如何实现多态？通过使用继承。你可以将继承和静态属性一起使用吗？当然不可以。

我认为静态属性违背了面向对象的概念，真正的面向对象的语言不应该加入静态属性。你应该尽可能使用单例模式而不是静态对象。

所以，为什么Java拥有静态属性却依然管自己叫面向对象的语言呢？我的看法是，由于一些历史的原因他们希望C++的开发者尽快的适应Java并尽可能的将他们吸引进Java的世界。

## 切换到完全没有静态属性的世界

直到上一篇文章（关于对象的创建），所有的Enkel的类都是静态的。它们包含主函数和其他的静态方法。一开始，允许Enkel语言拥有静态属性是为了先实现所有的基础的语言特性，如变量，条件语句，循环，方法调用等，然后再将它们切换到OO模式。现在是时候实现OO了。

### 关于主函数

所有的Java程序都需要定义静态的主函数。Enkel通过下面的方式来处理这个问题：

- 后台编译器生成静态的主函数
- 在主函数中，使用默认构造函数创建一个对象
- 它在新创建的对象上调用`start`方法
- 程序员提供一个`start`方法

```java
private Function getGeneratedMainMethod() {
    FunctionParameter args = new FunctionParameter("args", BultInType.STRING_ARR, Optional.empty());
    FunctionSignature functionSignature = new FunctionSignature("main", Collections.singletonList(args), BultInType.VOID);
    ConstructorCall constructorCall = new ConstructorCall(scope.getClassName());
    FunctionSignature startFunSignature = new FunctionSignature("start", Collections.emptyList(), BultInType.VOID);
    FunctionCall startFunctionCall = new FunctionCall(startFunSignature, Collections.emptyList(), scope.getClassType());
    Block block = new Block(new Scope(scope), Arrays.asList(constructorCall,startFunctionCall));
    return new Function(functionSignature, block);
 }
```

start方法基本就是非静态的main方法。

## INVOKESTATIC vs INVOKEVIRTUAL

在[第七节：方法](./06-方法.md)中，我使用`INVOKESTATIC`指令调用方法。现在换成`INVOKEVIRTUAL`。

在它们之间有一个重要的区别 - `INVOKEVIRTUAL`需要所有者（即对象实例）。`INVOKESTATIC`将参数从堆栈中弹出。`INVOKEVIRTUAL`先将所有者弹出堆栈，然后再将参数弹出，它强制生成所有者的表达式。

如果程序员在这里没有提供所有者，它将隐式的提供一个“this”变量的引用。

```java
//Mapping antlr generated FunctionCallContext to FunctionCall 
@Override
public Expression visitFunctionCall(@NotNull EnkelParser.FunctionCallContext ctx) {
    //other stuff
    boolean ownerIsExplicit = ctx.owner != null;
    if(ownerIsExplicit) {
        Expression owner = ctx.owner.accept(this);
        return new FunctionCall(signature, arguments, owner);
    }
    ClassType thisType = new ClassType(scope.getClassName());
    return new FunctionCall(signature, arguments, new VarReference("this",thisType)); //pass "this" as a owner 
}
```

```java
//Generating bytecode using mapped FunctionCall object
public void generate(FunctionCall functionCall) {
    functionCall.getOwner().accept(this); //generate owner (pushses it onto stack)
    generateArguments(functionCall);  //generate arguments
    String functionName = functionCall.getIdentifier();
    String methodDescriptor = DescriptorFactory.getMethodDescriptor(functionCall.getSignature());
    String ownerDescriptor = functionCall.getOwnerType().getInternalName();
    //Consumes owner and arguments off the stack
    methodVisitor.visitMethodInsn(Opcodes.INVOKEVIRTUAL, ownerDescriptor, functionName, methodDescriptor, false); 
}
```

## 示例

下面的Enkel类：

```groovy
HelloStart {
    start {
        print "Hey I am non-static 'start' method"
    }
}
```

编译后生成字节码：

```shell
kuba@kuba-laptop:~/repos/Enkel-JVM-language$ javap -c HelloStart.class 
public class HelloStart {
  public void start();
    Code:
       0: getstatic     #12                 // Field java/lang/System.out:Ljava/io/PrintStream;
       3: ldc           #14                 // String Hey I am non-static  'start' method
       5: invokevirtual #19                 // Method "Ljava/io/PrintStream;".println:(Ljava/lang/String;)V
       8: return

  //Constructor
  public HelloStart();
    Code:
       0: aload_0   //get "this"
       1: invokespecial #22                 // Method java/lang/Object."<init>":()V - call super
       4: return

  public static void main(java.lang.String[]);
    Code:
       0: new           #2                  // class HelloStart - create new object
       3: dup       //duplicate new object so that invokespecial does not consumes it
       4: invokespecial #25                 // Method "<init>":()V - call constructor
       7: invokevirtual #27                 // Method start:()V
      10: return
}
```

它与下面的Java代码等价：

```java
public class HelloStart {
    public HelloStart() {
    }

    public static void main(String[] var0) {
        (new HelloStart()).start();
    }
    
    public void start() {
        System.out.println("Hey I am non-static \'start\' method");
    }
}
```

</br></br></br>

<div align="left"><a href="./14-构造函数.md">上一节</a></div> 

<div align="left"><a href="./16-引用其他的类(包括Java Api).md">下一节</a></div> 